qiskit_qubit_reuse/__init__.py
qiskit_qubit_reuse/plugin.py
qiskit_qubit_reuse/qubit_reuse.py
qiskit_qubit_reuse/qubit_reuse_greedy.py
qiskit_qubit_reuse-0.0.2.dist-info/LICENSE.txt
qiskit_qubit_reuse-0.0.2.dist-info/METADATA
qiskit_qubit_reuse-0.0.2.dist-info/WHEEL
qiskit_qubit_reuse-0.0.2.dist-info/entry_points.txt
qiskit_qubit_reuse-0.0.2.dist-info/top_level.txt
qiskit_qubit_reuse-0.0.2.dist-info/RECORD
