Metadata-Version: 2.1
Name: qiskit-qubit-reuse
Version: 0.0.2
Summary: A Qiskit's compiler plugin to reuse qubits using midcircuit measurement
Author: Raynel Sanchez and Danielle Odigie
License: Apache 2.0
Keywords: qiskit sdk quantum
Classifier: Environment :: Console
Classifier: License :: OSI Approved :: Apache Software License
Classifier: Intended Audience :: Developers
Classifier: Intended Audience :: Science/Research
Classifier: Operating System :: Microsoft :: Windows
Classifier: Operating System :: MacOS
Classifier: Operating System :: POSIX :: Linux
Classifier: Programming Language :: Python :: 3 :: Only
Classifier: Programming Language :: Python :: 3.8
Classifier: Programming Language :: Python :: 3.9
Classifier: Programming Language :: Python :: 3.10
Classifier: Programming Language :: Python :: 3.11
Classifier: Topic :: Scientific/Engineering
Requires-Python: >=3.8
License-File: LICENSE.txt
Requires-Dist: qiskit >=0.43.0
Requires-Dist: rustworkx >=0.12.0
